ploomber_engine/__init__.py
ploomber_engine/_translator.py
ploomber_engine/_util.py
ploomber_engine/benchmark.py
ploomber_engine/cli.py
ploomber_engine/client.py
ploomber_engine/engine.py
ploomber_engine/execute.py
ploomber_engine/ipython.py
ploomber_engine/papermill.py
ploomber_engine/profiling.py
ploomber_engine/testing.py
ploomber_engine/tracking/__init__.py
ploomber_engine/tracking/__main__.py
ploomber_engine/tracking/io.py
ploomber_engine/tracking/tracking.py
ploomber_engine-0.0.33.dist-info/LICENSE
ploomber_engine-0.0.33.dist-info/METADATA
ploomber_engine-0.0.33.dist-info/WHEEL
ploomber_engine-0.0.33.dist-info/entry_points.txt
ploomber_engine-0.0.33.dist-info/top_level.txt
ploomber_engine-0.0.33.dist-info/RECORD
