Metadata-Version: 2.1
Name: ploomber-engine
Version: 0.0.33
Classifier: License :: OSI Approved :: BSD License
License-File: LICENSE
Requires-Dist: ploomber-core>=0.2
Requires-Dist: ploomber-extension
Requires-Dist: debuglater>=1.4.4
Requires-Dist: nbclient
Requires-Dist: ipython
Requires-Dist: parso
Requires-Dist: nbformat
Requires-Dist: click
Requires-Dist: tqdm
Requires-Dist: importlib-metadata; python_version < "3.8"
Requires-Dist: ipython<=8.12.0; python_version <= "3.8"
Provides-Extra: dev
Requires-Dist: pkgmt; extra == "dev"
Requires-Dist: pytest<8; extra == "dev"
Requires-Dist: flake8; extra == "dev"
Requires-Dist: invoke; extra == "dev"
Requires-Dist: twine; extra == "dev"
Requires-Dist: matplotlib; extra == "dev"
Requires-Dist: pandas; extra == "dev"
Requires-Dist: numpy; extra == "dev"
Requires-Dist: sklearn-evaluation; extra == "dev"
Requires-Dist: jupytext; extra == "dev"
Requires-Dist: psutil; extra == "dev"
